setup.py
Arl_Gauss_Binom/Binomialdistribution.py
Arl_Gauss_Binom/Gaussiandistribution.py
Arl_Gauss_Binom/Generaldistribution.py
Arl_Gauss_Binom/__init__.py
Arl_Gauss_Binom.egg-info/PKG-INFO
Arl_Gauss_Binom.egg-info/SOURCES.txt
Arl_Gauss_Binom.egg-info/dependency_links.txt
Arl_Gauss_Binom.egg-info/not-zip-safe
Arl_Gauss_Binom.egg-info/top_level.txt